Economics/__init__.py
Economics/microecon.py
Economical-1.5.6.dist-info/METADATA
Economical-1.5.6.dist-info/WHEEL
Economical-1.5.6.dist-info/top_level.txt
Economical-1.5.6.dist-info/RECORD
