Metadata-Version: 2.1
Name: Economical
Version: 1.5.6
Summary: library
Home-page: https://Economics.readthedocs.io/
Author: Ayush Gogne
Author-email: ayushgogne23@gmail.com
Classifier: Intended Audience :: Developers
Classifier: Programming Language :: Python
Classifier: Programming Language :: Python :: 3
Classifier: Programming Language :: Python :: 3.6
Classifier: Programming Language :: Python :: 3.7
Classifier: Programming Language :: Python :: 3.8
Classifier: Programming Language :: Python :: 3.9
Classifier: Operating System :: OS Independent
Requires-Dist: typing
